qudora_sdk/__init__.py
qudora_sdk/qiskit/__init__.py
qudora_sdk/qiskit/backend.py
qudora_sdk/qiskit/job.py
qudora_sdk/qiskit/provider.py
qudora_sdk/qiskit/util.py
qudora_sdk-1.1.4.dist-info/licenses/LICENSE
qudora_sdk-1.1.4.dist-info/METADATA
qudora_sdk-1.1.4.dist-info/WHEEL
qudora_sdk-1.1.4.dist-info/top_level.txt
qudora_sdk-1.1.4.dist-info/RECORD
