Metadata-Version: 2.4
Name: qudora_sdk
Version: 1.1.4
Summary: A tool to access the quantum devices from the QUDORA Cloud using Python.
Author-email: QUDORA Technologies GmbH <support@qudora.com>
License:                     GNU AFFERO GENERAL PUBLIC LICENSE
Project-URL: Homepage, https://cloud.qudora.com
Requires-Python: >=3.9
License-File: LICENSE
Requires-Dist: qiskit==2.1.2
Requires-Dist: requests~=2.32.0
Requires-Dist: websocket-client==1.8.0
Requires-Dist: openqasm3[all]==1.0.0
Provides-Extra: dev
Requires-Dist: pytest==8.0.0; extra == "dev"
Dynamic: license-file
